{
  "page_name": "page_12",
  "image_path": "D:\\1something\\Learning_Files\\newvl\\pdf_images\\1_四海_25下半年1期套题班_行测\\page_12.png",
  "questions": [
    {
      "qno": 26,
      "image": "1_四海_25下半年1期套题班_行测\\questions_page_12\\q26.png",
      "crop_box_image": [
        0,
        186,
        1574,
        510
      ],
      "crop_box_blocks": [
        210,
        201,
        1054,
        495
      ],
      "text_blocks": [
        {
          "bbox": [
            210,
            201,
            1054,
            495
          ],
          "text": "26．关于少数民族特色民居，下列说法错误的是：A．侗族居住的村寨一般具有依山傍水的特点\nB．蒙古包的结构简单，由木骨架和外覆的羊毛毡组成\nC．彝族民居中的炕，集床、椅子、客厅等多种功能于一身\nD．藏族碉房多用石头和土坯建造，屋顶平坦，便于晾晒粮食\n"
        }
      ],
      "table_blocks": [],
      "other_blocks": []
    },
    {
      "qno": 27,
      "image": "1_四海_25下半年1期套题班_行测\\questions_page_12\\q27.png",
      "crop_box_image": [
        0,
        512,
        1574,
        840
      ],
      "crop_box_blocks": [
        146,
        527,
        894,
        825
      ],
      "text_blocks": [
        {
          "bbox": [
            146,
            527,
            671,
            558
          ],
          "text": "27．下列与水资源有关说法错误的是："
        },
        {
          "bbox": [
            210,
            593,
            894,
            825
          ],
          "text": "A．我国主要淡水资源是冰川和地下水B．可以通过蒸发海水提取到氯化钠晶体C．利用蒸馏法淡化海水的过程主要是物理变化D．我国西北绝大部分地区属于地下水补给贫乏区"
        }
      ],
      "table_blocks": [],
      "other_blocks": []
    },
    {
      "qno": 28,
      "image": "1_四海_25下半年1期套题班_行测\\questions_page_12\\q28.png",
      "crop_box_image": [
        0,
        842,
        1574,
        1169
      ],
      "crop_box_blocks": [
        147,
        857,
        1194,
        1154
      ],
      "text_blocks": [
        {
          "bbox": [
            147,
            857,
            702,
            888
          ],
          "text": "28．关于急救知识，下列说法正确的是："
        },
        {
          "bbox": [
            210,
            923,
            1194,
            1154
          ],
          "text": "A．伤者出现呕吐时，应对其采取仰卧姿势放置，以防止窒息B．踝关节扭伤后，应及时采取热疗加上按摩的方式来促进血液循环C．冻伤后应使用温水复温，直至冻伤区域的皮肤恢复正常颜色和感觉D．心肺复苏需按照“胸外按压10次、人工呼吸2次”的流程循环操作"
        }
      ],
      "table_blocks": [],
      "other_blocks": []
    },
    {
      "qno": 29,
      "image": "1_四海_25下半年1期套题班_行测\\questions_page_12\\q29.png",
      "crop_box_image": [
        0,
        1172,
        1574,
        1500
      ],
      "crop_box_blocks": [
        147,
        1187,
        896,
        1485
      ],
      "text_blocks": [
        {
          "bbox": [
            147,
            1187,
            701,
            1218
          ],
          "text": "29．关于视力问题，下列说法错误的是："
        },
        {
          "bbox": [
            210,
            1253,
            896,
            1485
          ],
          "text": "A．青光眼是不可逆的致盲性眼病\n\nB．白内障的主要治疗方法是药物治疗\n\nC．在视觉发育关键时期的幼儿容易发生弱视\nD．色盲与色弱最主要的区别是对颜色的辨别能力\n"
        }
      ],
      "table_blocks": [],
      "other_blocks": []
    },
    {
      "qno": 30,
      "image": "1_四海_25下半年1期套题班_行测\\questions_page_12\\q30.png",
      "crop_box_image": [
        0,
        1502,
        1574,
        1829
      ],
      "crop_box_blocks": [
        148,
        1517,
        866,
        1814
      ],
      "text_blocks": [
        {
          "bbox": [
            148,
            1517,
            701,
            1548
          ],
          "text": "30．关于常见植物，下列说法正确的是："
        },
        {
          "bbox": [
            210,
            1583,
            866,
            1814
          ],
          "text": "A．香樟树抗旱耐盐碱，在北方地区更容易生长B．玉兰的花期在夏季，花朵有一定的药用价值C．银杏树现今已广泛种植，退出濒危植物名录D．侧柏四季常青，树形美观，常用作园林绿化"
        }
      ],
      "table_blocks": [],
      "other_blocks": [
        {
          "label": "number",
          "bbox": [
            669,
            2060,
            898,
            2088
          ],
          "content": "第8页共42页",
          "region_label": null
        }
      ]
    }
  ]
}